{
  "generated_at": "2026-05-09T20:10:36Z",
  "total_submissions": 10,
  "grid_size_free": 0.1,
  "grid_size_paid": 0.01,
  "cluster_neighbor_radius": 4,
  "cluster_min_neighbor_cells": 2,
  "cluster_min_avg_stars": 0.0,
  "free": {
    "type": "FeatureCollection",
    "features": [
      {
        "type": "Feature",
        "geometry": {
          "type": "Point",
          "coordinates": [
            140.6,
            37.5
          ]
        },
        "properties": {
          "weight": 1.0,
          "count": 4
        }
      },
      {
        "type": "Feature",
        "geometry": {
          "type": "Point",
          "coordinates": [
            140.2,
            35.1
          ]
        },
        "properties": {
          "weight": 0.5,
          "count": 2
        }
      },
      {
        "type": "Feature",
        "geometry": {
          "type": "Point",
          "coordinates": [
            141.0,
            41.3
          ]
        },
        "properties": {
          "weight": 0.25,
          "count": 1
        }
      },
      {
        "type": "Feature",
        "geometry": {
          "type": "Point",
          "coordinates": [
            141.4,
            41.3
          ]
        },
        "properties": {
          "weight": 0.25,
          "count": 1
        }
      },
      {
        "type": "Feature",
        "geometry": {
          "type": "Point",
          "coordinates": [
            141.6,
            40.4
          ]
        },
        "properties": {
          "weight": 0.25,
          "count": 1
        }
      },
      {
        "type": "Feature",
        "geometry": {
          "type": "Point",
          "coordinates": [
            137.9,
            36.7
          ]
        },
        "properties": {
          "weight": 0.25,
          "count": 1
        }
      },
      {
        "type": "Feature",
        "geometry": {
          "type": "Point",
          "coordinates": [
            141.3,
            41.1
          ]
        },
        "properties": {
          "weight": 0.25,
          "count": 1
        }
      },
      {
        "type": "Feature",
        "geometry": {
          "type": "Point",
          "coordinates": [
            141.4,
            40.6
          ]
        },
        "properties": {
          "weight": 0.25,
          "count": 1
        }
      },
      {
        "type": "Feature",
        "geometry": {
          "type": "Point",
          "coordinates": [
            140.6,
            36.0
          ]
        },
        "properties": {
          "weight": 0.25,
          "count": 1
        }
      },
      {
        "type": "Feature",
        "geometry": {
          "type": "Point",
          "coordinates": [
            141.8,
            39.6
          ]
        },
        "properties": {
          "weight": 0.25,
          "count": 1
        }
      },
      {
        "type": "Feature",
        "geometry": {
          "type": "Point",
          "coordinates": [
            141.8,
            40.0
          ]
        },
        "properties": {
          "weight": 0.25,
          "count": 1
        }
      },
      {
        "type": "Feature",
        "geometry": {
          "type": "Point",
          "coordinates": [
            141.3,
            40.8
          ]
        },
        "properties": {
          "weight": 0.25,
          "count": 1
        }
      },
      {
        "type": "Feature",
        "geometry": {
          "type": "Point",
          "coordinates": [
            138.1,
            35.5
          ]
        },
        "properties": {
          "weight": 0.25,
          "count": 1
        }
      }
    ]
  },
  "paid": {
    "type": "FeatureCollection",
    "features": [
      {
        "type": "Feature",
        "geometry": {
          "type": "Point",
          "coordinates": [
            140.54497,
            35.975127
          ]
        },
        "properties": {
          "weight": 1.0,
          "count": 1,
          "avg_stars": 3.0
        }
      },
      {
        "type": "Feature",
        "geometry": {
          "type": "Point",
          "coordinates": [
            138.126983,
            35.517942
          ]
        },
        "properties": {
          "weight": 1.0,
          "count": 1,
          "avg_stars": 3.0
        }
      },
      {
        "type": "Feature",
        "geometry": {
          "type": "Point",
          "coordinates": [
            140.212318,
            35.048834
          ]
        },
        "properties": {
          "weight": 0.0667,
          "count": 2,
          "avg_stars": 0.0
        }
      },
      {
        "type": "Feature",
        "geometry": {
          "type": "Point",
          "coordinates": [
            141.022558,
            41.353699
          ]
        },
        "properties": {
          "weight": 0.0333,
          "count": 1,
          "avg_stars": 0.0
        }
      },
      {
        "type": "Feature",
        "geometry": {
          "type": "Point",
          "coordinates": [
            141.337344,
            41.287114
          ]
        },
        "properties": {
          "weight": 0.0333,
          "count": 1,
          "avg_stars": 0.0
        }
      },
      {
        "type": "Feature",
        "geometry": {
          "type": "Point",
          "coordinates": [
            141.559693,
            40.335127
          ]
        },
        "properties": {
          "weight": 0.0333,
          "count": 1,
          "avg_stars": 0.0
        }
      },
      {
        "type": "Feature",
        "geometry": {
          "type": "Point",
          "coordinates": [
            141.862889,
            39.64557
          ]
        },
        "properties": {
          "weight": 0.0333,
          "count": 1,
          "avg_stars": 0.0
        }
      },
      {
        "type": "Feature",
        "geometry": {
          "type": "Point",
          "coordinates": [
            141.733234,
            39.999717
          ]
        },
        "properties": {
          "weight": 0.0333,
          "count": 1,
          "avg_stars": 0.0
        }
      },
      {
        "type": "Feature",
        "geometry": {
          "type": "Point",
          "coordinates": [
            141.24171,
            40.740721
          ]
        },
        "properties": {
          "weight": 0.0333,
          "count": 1,
          "avg_stars": 0.0
        }
      }
    ]
  }
}